axl/__init__.py
axl/cli.py
axl/logging.py
axl/compiler/__init__.py
axl/compiler/argo.py
axl/core/__init__.py
axl/core/decorators.py
axl/core/workflow.py
axl/io/__init__.py
axl/io/protocol.py
axl/io/registry.py
axl/io/storage.py
axl/io/handlers/__init__.py
axl/io/handlers/cloudpickle.py
axl/io/handlers/pickle.py
axl/ir/__init__.py
axl/ir/builder.py
axl/ir/nodes.py
axl/ir/outputs.py
axl/ir/workflow.py
axl/runtime/__init__.py
axl/runtime/__main__.py
axl/runtime/local.py
axl_workflows-0.2.0.dist-info/METADATA
axl_workflows-0.2.0.dist-info/WHEEL
axl_workflows-0.2.0.dist-info/entry_points.txt
axl_workflows-0.2.0.dist-info/licenses/LICENSE
axl_workflows-0.2.0.dist-info/RECORD
