Metadata-Version: 2.4
Name: axl-workflows
Version: 0.2.0
Summary: Lightweight framework for building data and ML workflows with class-based Python syntax
Project-URL: Homepage, https://github.com/pedrospinosa/axl-workflows
Project-URL: Documentation, https://axl-workflows.readthedocs.io/
Project-URL: Repository, https://github.com/pedrospinosa/axl-workflows
Project-URL: Bug Tracker, https://github.com/pedrospinosa/axl-workflows/issues
Project-URL: Changelog, https://github.com/pedrospinosa/axl-workflows/blob/main/CHANGELOG.md
Project-URL: Release Notes, https://github.com/pedrospinosa/axl-workflows/releases
Author-email: AXL Workflows Contributors <contributors@axl-workflows.dev>
Maintainer-email: AXL Workflows Contributors <contributors@axl-workflows.dev>
License: MIT
License-File: LICENSE
Keywords: argo,dagster,data,kubeflow,kubernetes,ml,workflow
Classifier: Development Status :: 3 - Alpha
Classifier: Intended Audience :: Developers
Classifier: Intended Audience :: Science/Research
Classifier: License :: OSI Approved :: MIT License
Classifier: Operating System :: OS Independent
Classifier: Programming Language :: Python :: 3
Classifier: Programming Language :: Python :: 3.10
Classifier: Programming Language :: Python :: 3.11
Classifier: Programming Language :: Python :: 3.12
Classifier: Topic :: Scientific/Engineering :: Artificial Intelligence
Classifier: Topic :: Software Development :: Libraries :: Python Modules
Classifier: Topic :: System :: Distributed Computing
Requires-Python: >=3.10
Requires-Dist: cloudpickle>=3.0.0
Requires-Dist: pydantic>=2.0.0
Requires-Dist: pyyaml>=6.0.0
Requires-Dist: rich>=13.0.0
Requires-Dist: typer>=0.9.0
Provides-Extra: all
Requires-Dist: dagster-graphql>=1.5.0; extra == 'all'
Requires-Dist: dagster>=1.5.0; extra == 'all'
Requires-Dist: kubernetes>=28.0.0; extra == 'all'
Requires-Dist: pyyaml>=6.0.0; extra == 'all'
Provides-Extra: argo
Requires-Dist: kubernetes>=28.0.0; extra == 'argo'
Requires-Dist: pyyaml>=6.0.0; extra == 'argo'
Provides-Extra: dagster
Requires-Dist: dagster-graphql>=1.5.0; extra == 'dagster'
Requires-Dist: dagster>=1.5.0; extra == 'dagster'
Provides-Extra: dev
Requires-Dist: black>=23.0.0; extra == 'dev'
Requires-Dist: mypy>=1.0.0; extra == 'dev'
Requires-Dist: pre-commit>=3.0.0; extra == 'dev'
Requires-Dist: pytest-cov>=4.0.0; extra == 'dev'
Requires-Dist: pytest-mock>=3.10.0; extra == 'dev'
Requires-Dist: pytest>=7.0.0; extra == 'dev'
Requires-Dist: ruff>=0.1.0; extra == 'dev'
Requires-Dist: scikit-learn>=1.3.0; extra == 'dev'
Requires-Dist: twine>=4.0.0; extra == 'dev'
Requires-Dist: types-pyyaml>=6.0.0; extra == 'dev'
